upt/__init__.py
upt/checksum.py
upt/exceptions.py
upt/licenses.py
upt/log.py
upt/upt.py
upt/tests/__init__.py
upt/tests/test_checksum.py
upt/tests/test_licenses.py
upt/tests/test_log.py
upt/tests/test_upt.py
upt-0.12.data/data/share/man/man1/upt.1
upt-0.12.dist-info/LICENSE
upt-0.12.dist-info/METADATA
upt-0.12.dist-info/WHEEL
upt-0.12.dist-info/entry_points.txt
upt-0.12.dist-info/top_level.txt
upt-0.12.dist-info/RECORD
