Metadata-Version: 2.1
Name: upt
Version: 0.12
Summary: Package software from any package manager to any distribution
Home-page: https://framagit.org/upt/upt
Author: Cyril Roelandt
Author-email: tipecaml@gmail.com
License: BSD-3-Clause
Platform: UNKNOWN
Classifier: Development Status :: 3 - Alpha
Classifier: Intended Audience :: Developers
Classifier: License :: OSI Approved :: BSD License
Classifier: Programming Language :: Python :: 3
Classifier: Programming Language :: Python :: 3.6
Classifier: Programming Language :: Python :: 3.7
Classifier: Programming Language :: Python :: 3.8
Classifier: Programming Language :: Python :: 3.9
Classifier: Programming Language :: Python :: 3 :: Only
Requires-Dist: packaging
Requires-Dist: setuptools
Requires-Dist: spdx-lookup
Provides-Extra: backends
Requires-Dist: upt-fedora ; extra == 'backends'
Requires-Dist: upt-freebsd ; extra == 'backends'
Requires-Dist: upt-guix ; extra == 'backends'
Requires-Dist: upt-nix ; extra == 'backends'
Requires-Dist: upt-openbsd ; extra == 'backends'
Provides-Extra: color
Requires-Dist: colorlog (>5.0.1) ; extra == 'color'
Provides-Extra: frontends
Requires-Dist: upt-cpan ; extra == 'frontends'
Requires-Dist: upt-pypi ; extra == 'frontends'
Requires-Dist: upt-rubygems ; extra == 'frontends'
